boostrsa/__init__.py
boostrsa/boostrsa_types.py
boostrsa/searchlight.py
boostrsa/cores/__init__.py
boostrsa/cores/cpgpu/__init__.py
boostrsa/cores/cpgpu/stats.py
boostrsa/cores/cpu/__init__.py
boostrsa/cores/cpu/mask.py
boostrsa/cores/cpu/matrix.py
boostrsa/cores/gpu/__init__.py
boostrsa/cores/gpu/basic_operations.py
boostrsa/cores/gpu/mask.py
boostrsa/cores/gpu/matrix.py
boostrsa-0.0.1.dev9.dist-info/licenses/LICENSE.txt
boostrsa-0.0.1.dev9.dist-info/METADATA
boostrsa-0.0.1.dev9.dist-info/WHEEL
boostrsa-0.0.1.dev9.dist-info/top_level.txt
boostrsa-0.0.1.dev9.dist-info/RECORD
