Metadata-Version: 2.4
Name: boostrsa
Version: 0.0.1.dev9
Summary: This is toolbox for boosting calculation speed using GPU
Home-page: https://github.com/SeojinYoon/boostrsa.git
Author: seojin
Author-email: pures1@hanyang.ac.kr
Classifier: Programming Language :: Python :: 3
Classifier: License :: OSI Approved :: MIT License
Classifier: Operating System :: OS Independent
Requires-Python: >=3.8
License-File: LICENSE.txt
Requires-Dist: numpy
Requires-Dist: pandas
Requires-Dist: tqdm
Dynamic: author
Dynamic: author-email
Dynamic: classifier
Dynamic: description
Dynamic: description-content-type
Dynamic: home-page
Dynamic: license-file
Dynamic: requires-dist
Dynamic: requires-python
Dynamic: summary
